BUGS.txt
CHANGES.txt
COPYING
INSTALL.txt
LICENSE.txt
MANIFEST.in
README.rst
ez_setup.py
setup.cfg
setup.py
pychangelog/__init__.py
pychangelog/tests.py
pychangelog/version.py
pychangelog.egg-info/PKG-INFO
pychangelog.egg-info/SOURCES.txt
pychangelog.egg-info/dependency_links.txt
pychangelog.egg-info/requires.txt
pychangelog.egg-info/top_level.txt
sphinx/Makefile
sphinx/requirements.pip
sphinx/source/LICENSE.rst
sphinx/source/README.rst
sphinx/source/__package__.rst
sphinx/source/conf.py
sphinx/source/index.rst
sphinx/source/tests.rst
sphinx/source/version.rst