Metadata-Version: 1.1
Name: pychangelog
Version: 1.0.0.0-r1
Summary: Manage changelog files.
Home-page: https://bitbucket.org/bmearns/pychangelog
Author: Brian Mearns
Author-email: bmearns@ieee.org
License: LICENSE.txt
Platform: UNKNOWN
Classifier: License :: OSI Approved :: GNU General Public License v3 (GPLv3)
Classifier: Natural Language :: English
Classifier: Operating System :: OS Independent
Requires: docit
